turfik/__init__.py
turfik/centroid.py
turfik/destination.py
turfik/distance.py
turfik/helpers.py
turfik/invariant.py
turfik/rhumb_bearing.py
turfik/rhumb_destination.py
turfik/rhumb_distance.py
turfik/transform_rotate.py
turfik/transform_translate.py
turfik-0.0.2.dist-info/METADATA
turfik-0.0.2.dist-info/WHEEL
turfik-0.0.2.dist-info/top_level.txt
turfik-0.0.2.dist-info/RECORD
